Metadata-Version: 2.1
Name: polystores
Version: 0.2.5
Summary: Polystores is an abstraction and a collection of clients to interact with cloud storages.
Home-page: https://github.com/polyaxon/polystores
Author: Mourad Mourafiq
Author-email: mourad@polyaxon.com
Maintainer: Mourad Mourafiq
Maintainer-email: mourad@polyaxon.com
License: MIT
Keywords: polyaxon,aws,s3,microsoft,azure,google cloud storage,gcs,machine-learning,data-science,artificial-intelligence,ai,reinforcement-learning,kubernetes,docker
Platform: any
Classifier: Programming Language :: Python
Classifier: Operating System :: OS Independent
Classifier: Intended Audience :: Developers
Classifier: Intended Audience :: Science/Research
Classifier: Topic :: Scientific/Engineering :: Artificial Intelligence
Requires-Dist: rhea (>=0.5.5)
Provides-Extra: azure
Requires-Dist: azure-storage ; extra == 'azure'
Provides-Extra: gcs
Requires-Dist: google-cloud-storage ; extra == 'gcs'
Provides-Extra: s3
Requires-Dist: boto3 ; extra == 's3'
Requires-Dist: botocore ; extra == 's3'
